README.md
setup.cfg
setup.py
ocr_rule/__init__.py
ocr_rule/rule.py
ocr_rule.egg-info/PKG-INFO
ocr_rule.egg-info/SOURCES.txt
ocr_rule.egg-info/dependency_links.txt
ocr_rule.egg-info/top_level.txt