Metadata-Version: 2.1
Name: ocr_rule
Version: 0.7
Summary: qoala ocr rule
Home-page: UNKNOWN
Author: qoala-ai-team
Author-email: fatchur.rahman@qoala.id
License: UNKNOWN
Platform: UNKNOWN
